{
    "groups": [
        {
            "destination_root": {
                "linux": "@HOME",
                "windows": "@HOME"
            },
            "entries": [
                {
                    "source": "git/.gitconfig",
                    "destination": ".config/git/config",
                    "action": "symlink"
                },
                {
                    "source": "latexmk/.latexmkrc",
                    "destination": ".config/latexmk/latexmkrc",
                    "action": "symlink"
                }
            ]
        },
        {
            "destination_root": {
                "linux": "@HOME"
            },
            "entries": [
                {
                    "source": "tmux/tmux.conf",
                    "destination": ".config/tmux/tmux.conf",
                    "action": "symlink"
                },
                {
                    "source": "vim/.vimrc",
                    "destination": ".vimrc",
                    "action": "symlink"
                },
                {
                    "source": "fish/conf.d/mysetup.fish",
                    "destination": ".config/fish/conf.d/mysetup.fish",
                    "action": "symlink"
                }
            ]
        },
        {
            "destination_root": {
                "linux": "@HOME/projectroot",
                "windows": "D:\\projectroot"
            },
            "entries": [
                {
                    "source": "editorconfig/.editorconfig",
                    "destination": ".editorconfig",
                    "action": "symlink"
                },
                {
                    "source": "clang/.clang-format",
                    "destination": ".clang-format",
                    "action": "symlink"
                },
                {
                    "source": "clang/.clang-tidy",
                    "destination": ".clang-tidy",
                    "action": "symlink"
                }
            ]
        },
        {
            "destination_root": {
                "windows": "@PSHOME"
            },
            "entries": [
                {
                    "source": "pwsh\\simple_pwsh_utils",
                    "destination": "simple_pwsh_utils",
                    "action": "copy"
                },
                {
                    "source": "pwsh\\Microsoft.PowerShell_profile.ps1",
                    "destination": "..\\Microsoft.PowerShell_profile.ps1",
                    "action": "copy"
                }
            ]
        }
    ]
}
